[
    {
        "captured_at": "2016-07-21T02:20:52.000Z",
        "channel_id": null,
        "device_id": 100222,
        "devicetype_id": "Pointcast V1",
        "height": 13,
        "id": 68660930,
        "latitude": 31.833193,
        "location_name": null,
        "longitude": 130.301922,
        "original_id": 68660930,
        "sensor_id": null,
        "station_id": null,
        "unit": "cpm",
        "user_id": 759,
        "value": 20.0
    },
    {
        "captured_at": "2016-07-21T02:30:57.000Z",
        "channel_id": null,
        "device_id": 100222,
        "devicetype_id": "Pointcast V1",
        "height": 13,
        "id": 68661054,
        "latitude": 31.833193,
        "location_name": null,
        "longitude": 130.301922,
        "original_id": 68661054,
        "sensor_id": null,
        "station_id": null,
        "unit": "cpm",
        "user_id": 759,
        "value": 11.0
    },
    {
        "captured_at": "2016-07-21T02:36:00.000Z",
        "channel_id": null,
        "device_id": 100222,
        "devicetype_id": "Pointcast V1",
        "height": 13,
        "id": 68661117,
        "latitude": 31.833193,
        "location_name": null,
        "longitude": 130.301922,
        "original_id": 68661117,
        "sensor_id": null,
        "station_id": null,
        "unit": "cpm",
        "user_id": 759,
        "value": 14.0
    },
    {
        "captured_at": "2016-07-21T02:41:02.000Z",
        "channel_id": null,
        "device_id": 100222,
        "devicetype_id": "Pointcast V1",
        "height": 13,
        "id": 68661179,
        "latitude": 31.833193,
        "location_name": null,
        "longitude": 130.301922,
        "original_id": 68661179,
        "sensor_id": null,
        "station_id": null,
        "unit": "cpm",
        "user_id": 759,
        "value": 16.0
    },
    {
        "captured_at": "2016-07-21T02:46:05.000Z",
        "channel_id": null,
        "device_id": 100222,
        "devicetype_id": "Pointcast V1",
        "height": 13,
        "id": 68661242,
        "latitude": 31.833193,
        "location_name": null,
        "longitude": 130.301922,
        "original_id": 68661242,
        "sensor_id": null,
        "station_id": null,
        "unit": "cpm",
        "user_id": 759,
        "value": 11.0
    },
    {
        "captured_at": "2016-07-21T02:56:10.000Z",
        "channel_id": null,
        "device_id": 100222,
        "devicetype_id": "Pointcast V1",
        "height": 13,
        "id": 68661366,
        "latitude": 31.833193,
        "location_name": null,
        "longitude": 130.301922,
        "original_id": 68661366,
        "sensor_id": null,
        "station_id": null,
        "unit": "cpm",
        "user_id": 759,
        "value": 13.0
    },
    {
        "captured_at": "2016-07-21T02:51:08.000Z",
        "channel_id": null,
        "device_id": 100222,
        "devicetype_id": "Pointcast V1",
        "height": 13,
        "id": 68661307,
        "latitude": 31.833193,
        "location_name": null,
        "longitude": 130.301922,
        "original_id": 68661307,
        "sensor_id": null,
        "station_id": null,
        "unit": "cpm",
        "user_id": 759,
        "value": 12.0
    },
    {
        "captured_at": "2016-07-21T03:01:13.000Z",
        "channel_id": null,
        "device_id": 100222,
        "devicetype_id": "Pointcast V1",
        "height": 13,
        "id": 68661425,
        "latitude": 31.833193,
        "location_name": null,
        "longitude": 130.301922,
        "original_id": 68661425,
        "sensor_id": null,
        "station_id": null,
        "unit": "cpm",
        "user_id": 759,
        "value": 20.0
    },
    {
        "captured_at": "2016-07-21T03:06:16.000Z",
        "channel_id": null,
        "device_id": 100222,
        "devicetype_id": "Pointcast V1",
        "height": 13,
        "id": 68661487,
        "latitude": 31.833193,
        "location_name": null,
        "longitude": 130.301922,
        "original_id": 68661487,
        "sensor_id": null,
        "station_id": null,
        "unit": "cpm",
        "user_id": 759,
        "value": 15.0
    },
    {
        "captured_at": "2016-07-21T03:16:21.000Z",
        "channel_id": null,
        "device_id": 100222,
        "devicetype_id": "Pointcast V1",
        "height": 13,
        "id": 68661604,
        "latitude": 31.833193,
        "location_name": null,
        "longitude": 130.301922,
        "original_id": 68661604,
        "sensor_id": null,
        "station_id": null,
        "unit": "cpm",
        "user_id": 759,
        "value": 13.0
    },
    {
        "captured_at": "2016-07-21T03:11:18.000Z",
        "channel_id": null,
        "device_id": 100222,
        "devicetype_id": "Pointcast V1",
        "height": 13,
        "id": 68661545,
        "latitude": 31.833193,
        "location_name": null,
        "longitude": 130.301922,
        "original_id": 68661545,
        "sensor_id": null,
        "station_id": null,
        "unit": "cpm",
        "user_id": 759,
        "value": 14.0
    },
    {
        "captured_at": "2016-07-21T03:26:26.000Z",
        "channel_id": null,
        "device_id": 100222,
        "devicetype_id": "Pointcast V1",
        "height": 13,
        "id": 68661727,
        "latitude": 31.833193,
        "location_name": null,
        "longitude": 130.301922,
        "original_id": 68661727,
        "sensor_id": null,
        "station_id": null,
        "unit": "cpm",
        "user_id": 759,
        "value": 16.0
    },
    {
        "captured_at": "2016-07-21T03:21:24.000Z",
        "channel_id": null,
        "device_id": 100222,
        "devicetype_id": "Pointcast V1",
        "height": 13,
        "id": 68661664,
        "latitude": 31.833193,
        "location_name": null,
        "longitude": 130.301922,
        "original_id": 68661664,
        "sensor_id": null,
        "station_id": null,
        "unit": "cpm",
        "user_id": 759,
        "value": 9.0
    },
    {
        "captured_at": "2016-07-21T03:41:34.000Z",
        "channel_id": null,
        "device_id": 100222,
        "devicetype_id": "Pointcast V1",
        "height": 13,
        "id": 68661909,
        "latitude": 31.833193,
        "location_name": null,
        "longitude": 130.301922,
        "original_id": 68661909,
        "sensor_id": null,
        "station_id": null,
        "unit": "cpm",
        "user_id": 759,
        "value": 8.0
    },
    {
        "captured_at": "2016-07-21T03:51:40.000Z",
        "channel_id": null,
        "device_id": 100222,
        "devicetype_id": "Pointcast V1",
        "height": 13,
        "id": 68662029,
        "latitude": 31.833193,
        "location_name": null,
        "longitude": 130.301922,
        "original_id": 68662029,
        "sensor_id": null,
        "station_id": null,
        "unit": "cpm",
        "user_id": 759,
        "value": 17.0
    },
    {
        "captured_at": "2016-07-21T03:31:29.000Z",
        "channel_id": null,
        "device_id": 100222,
        "devicetype_id": "Pointcast V1",
        "height": 13,
        "id": 68661789,
        "latitude": 31.833193,
        "location_name": null,
        "longitude": 130.301922,
        "original_id": 68661789,
        "sensor_id": null,
        "station_id": null,
        "unit": "cpm",
        "user_id": 759,
        "value": 14.0
    },
    {
        "captured_at": "2016-07-21T03:46:37.000Z",
        "channel_id": null,
        "device_id": 100222,
        "devicetype_id": "Pointcast V1",
        "height": 13,
        "id": 68661967,
        "latitude": 31.833193,
        "location_name": null,
        "longitude": 130.301922,
        "original_id": 68661967,
        "sensor_id": null,
        "station_id": null,
        "unit": "cpm",
        "user_id": 759,
        "value": 10.0
    },
    {
        "captured_at": "2016-07-21T03:36:32.000Z",
        "channel_id": null,
        "device_id": 100222,
        "devicetype_id": "Pointcast V1",
        "height": 13,
        "id": 68661851,
        "latitude": 31.833193,
        "location_name": null,
        "longitude": 130.301922,
        "original_id": 68661851,
        "sensor_id": null,
        "station_id": null,
        "unit": "cpm",
        "user_id": 759,
        "value": 13.0
    },
    {
        "captured_at": "2016-07-21T04:01:45.000Z",
        "channel_id": null,
        "device_id": 100222,
        "devicetype_id": "Pointcast V1",
        "height": 13,
        "id": 68662153,
        "latitude": 31.833193,
        "location_name": null,
        "longitude": 130.301922,
        "original_id": 68662153,
        "sensor_id": null,
        "station_id": null,
        "unit": "cpm",
        "user_id": 759,
        "value": 14.0
    },
    {
        "captured_at": "2016-07-21T03:56:42.000Z",
        "channel_id": null,
        "device_id": 100222,
        "devicetype_id": "Pointcast V1",
        "height": 13,
        "id": 68662091,
        "latitude": 31.833193,
        "location_name": null,
        "longitude": 130.301922,
        "original_id": 68662091,
        "sensor_id": null,
        "station_id": null,
        "unit": "cpm",
        "user_id": 759,
        "value": 7.0
    },
    {
        "captured_at": "2016-07-21T04:21:56.000Z",
        "channel_id": null,
        "device_id": 100222,
        "devicetype_id": "Pointcast V1",
        "height": 13,
        "id": 68662401,
        "latitude": 31.833193,
        "location_name": null,
        "longitude": 130.301922,
        "original_id": 68662401,
        "sensor_id": null,
        "station_id": null,
        "unit": "cpm",
        "user_id": 759,
        "value": 15.0
    },
    {
        "captured_at": "2016-07-21T04:11:51.000Z",
        "channel_id": null,
        "device_id": 100222,
        "devicetype_id": "Pointcast V1",
        "height": 13,
        "id": 68662277,
        "latitude": 31.833193,
        "location_name": null,
        "longitude": 130.301922,
        "original_id": 68662277,
        "sensor_id": null,
        "station_id": null,
        "unit": "cpm",
        "user_id": 759,
        "value": 11.0
    },
    {
        "captured_at": "2016-07-21T04:16:54.000Z",
        "channel_id": null,
        "device_id": 100222,
        "devicetype_id": "Pointcast V1",
        "height": 13,
        "id": 68662339,
        "latitude": 31.833193,
        "location_name": null,
        "longitude": 130.301922,
        "original_id": 68662339,
        "sensor_id": null,
        "station_id": null,
        "unit": "cpm",
        "user_id": 759,
        "value": 17.0
    },
    {
        "captured_at": "2016-07-21T04:06:48.000Z",
        "channel_id": null,
        "device_id": 100222,
        "devicetype_id": "Pointcast V1",
        "height": 13,
        "id": 68662215,
        "latitude": 31.833193,
        "location_name": null,
        "longitude": 130.301922,
        "original_id": 68662215,
        "sensor_id": null,
        "station_id": null,
        "unit": "cpm",
        "user_id": 759,
        "value": 11.0
    },
    {
        "captured_at": "2016-07-21T04:32:02.000Z",
        "channel_id": null,
        "device_id": 100222,
        "devicetype_id": "Pointcast V1",
        "height": 13,
        "id": 68662522,
        "latitude": 31.833193,
        "location_name": null,
        "longitude": 130.301922,
        "original_id": 68662522,
        "sensor_id": null,
        "station_id": null,
        "unit": "cpm",
        "user_id": 759,
        "value": 14.0
    }
]