[
    {
        "captured_at": "2016-07-09T07:32:30.000Z",
        "channel_id": null,
        "device_id": 100111,
        "devicetype_id": "Pointcast V1",
        "height": 5,
        "id": 67761158,
        "latitude": 32.475932,
        "location_name": null,
        "longitude": 130.607123,
        "original_id": 67761158,
        "sensor_id": null,
        "station_id": null,
        "unit": "cpm",
        "user_id": 759,
        "value": 65.0
    },
    {
        "captured_at": "2016-07-09T07:47:50.000Z",
        "channel_id": null,
        "device_id": 100111,
        "devicetype_id": "Pointcast V1",
        "height": 5,
        "id": 67761332,
        "latitude": 32.475932,
        "location_name": null,
        "longitude": 130.607123,
        "original_id": 67761332,
        "sensor_id": null,
        "station_id": null,
        "unit": "cpm",
        "user_id": 759,
        "value": 71.0
    },
    {
        "captured_at": "2016-07-09T07:52:56.000Z",
        "channel_id": null,
        "device_id": 100111,
        "devicetype_id": "Pointcast V1",
        "height": 5,
        "id": 67761390,
        "latitude": 32.475932,
        "location_name": null,
        "longitude": 130.607123,
        "original_id": 67761390,
        "sensor_id": null,
        "station_id": null,
        "unit": "cpm",
        "user_id": 759,
        "value": 66.0
    },
    {
        "captured_at": "2016-07-09T08:13:20.000Z",
        "channel_id": null,
        "device_id": 100111,
        "devicetype_id": "Pointcast V1",
        "height": 5,
        "id": 67761623,
        "latitude": 32.475932,
        "location_name": null,
        "longitude": 130.607123,
        "original_id": 67761623,
        "sensor_id": null,
        "station_id": null,
        "unit": "cpm",
        "user_id": 759,
        "value": 54.0
    },
    {
        "captured_at": "2016-07-09T08:08:14.000Z",
        "channel_id": null,
        "device_id": 100111,
        "devicetype_id": "Pointcast V1",
        "height": 5,
        "id": 67761566,
        "latitude": 32.475932,
        "location_name": null,
        "longitude": 130.607123,
        "original_id": 67761566,
        "sensor_id": null,
        "station_id": null,
        "unit": "cpm",
        "user_id": 759,
        "value": 59.0
    },
    {
        "captured_at": "2016-07-09T08:28:38.000Z",
        "channel_id": null,
        "device_id": 100111,
        "devicetype_id": "Pointcast V1",
        "height": 5,
        "id": 67761795,
        "latitude": 32.475932,
        "location_name": null,
        "longitude": 130.607123,
        "original_id": 67761795,
        "sensor_id": null,
        "station_id": null,
        "unit": "cpm",
        "user_id": 759,
        "value": 57.0
    },
    {
        "captured_at": "2016-07-09T08:03:09.000Z",
        "channel_id": null,
        "device_id": 100111,
        "devicetype_id": "Pointcast V1",
        "height": 5,
        "id": 67761506,
        "latitude": 32.475932,
        "location_name": null,
        "longitude": 130.607123,
        "original_id": 67761506,
        "sensor_id": null,
        "station_id": null,
        "unit": "cpm",
        "user_id": 759,
        "value": 55.0
    },
    {
        "captured_at": "2016-07-09T08:18:26.000Z",
        "channel_id": null,
        "device_id": 100111,
        "devicetype_id": "Pointcast V1",
        "height": 5,
        "id": 67761681,
        "latitude": 32.475932,
        "location_name": null,
        "longitude": 130.607123,
        "original_id": 67761681,
        "sensor_id": null,
        "station_id": null,
        "unit": "cpm",
        "user_id": 759,
        "value": 67.0
    },
    {
        "captured_at": "2016-07-09T07:58:01.000Z",
        "channel_id": null,
        "device_id": 100111,
        "devicetype_id": "Pointcast V1",
        "height": 5,
        "id": 67761448,
        "latitude": 32.475932,
        "location_name": null,
        "longitude": 130.607123,
        "original_id": 67761448,
        "sensor_id": null,
        "station_id": null,
        "unit": "cpm",
        "user_id": 759,
        "value": 57.0
    },
    {
        "captured_at": "2016-07-09T08:23:32.000Z",
        "channel_id": null,
        "device_id": 100111,
        "devicetype_id": "Pointcast V1",
        "height": 5,
        "id": 67761737,
        "latitude": 32.475932,
        "location_name": null,
        "longitude": 130.607123,
        "original_id": 67761737,
        "sensor_id": null,
        "station_id": null,
        "unit": "cpm",
        "user_id": 759,
        "value": 56.0
    },
    {
        "captured_at": "2016-07-09T08:43:56.000Z",
        "channel_id": null,
        "device_id": 100111,
        "devicetype_id": "Pointcast V1",
        "height": 5,
        "id": 67761971,
        "latitude": 32.475932,
        "location_name": null,
        "longitude": 130.607123,
        "original_id": 67761971,
        "sensor_id": null,
        "station_id": null,
        "unit": "cpm",
        "user_id": 759,
        "value": 61.0
    },
    {
        "captured_at": "2016-07-09T08:38:51.000Z",
        "channel_id": null,
        "device_id": 100111,
        "devicetype_id": "Pointcast V1",
        "height": 5,
        "id": 67761914,
        "latitude": 32.475932,
        "location_name": null,
        "longitude": 130.607123,
        "original_id": 67761914,
        "sensor_id": null,
        "station_id": null,
        "unit": "cpm",
        "user_id": 759,
        "value": 55.0
    },
    {
        "captured_at": "2016-07-09T08:49:03.000Z",
        "channel_id": null,
        "device_id": 100111,
        "devicetype_id": "Pointcast V1",
        "height": 5,
        "id": 67762029,
        "latitude": 32.475932,
        "location_name": null,
        "longitude": 130.607123,
        "original_id": 67762029,
        "sensor_id": null,
        "station_id": null,
        "unit": "cpm",
        "user_id": 759,
        "value": 50.0
    },
    {
        "captured_at": "2016-07-09T08:33:44.000Z",
        "channel_id": null,
        "device_id": 100111,
        "devicetype_id": "Pointcast V1",
        "height": 5,
        "id": 67761853,
        "latitude": 32.475932,
        "location_name": null,
        "longitude": 130.607123,
        "original_id": 67761853,
        "sensor_id": null,
        "station_id": null,
        "unit": "cpm",
        "user_id": 759,
        "value": 57.0
    },
    {
        "captured_at": "2016-07-09T08:54:08.000Z",
        "channel_id": null,
        "device_id": 100111,
        "devicetype_id": "Pointcast V1",
        "height": 5,
        "id": 67762088,
        "latitude": 32.475932,
        "location_name": null,
        "longitude": 130.607123,
        "original_id": 67762088,
        "sensor_id": null,
        "station_id": null,
        "unit": "cpm",
        "user_id": 759,
        "value": 53.0
    },
    {
        "captured_at": "2016-07-09T08:59:15.000Z",
        "channel_id": null,
        "device_id": 100111,
        "devicetype_id": "Pointcast V1",
        "height": 5,
        "id": 67762147,
        "latitude": 32.475932,
        "location_name": null,
        "longitude": 130.607123,
        "original_id": 67762147,
        "sensor_id": null,
        "station_id": null,
        "unit": "cpm",
        "user_id": 759,
        "value": 56.0
    },
    {
        "captured_at": "2016-07-09T09:09:26.000Z",
        "channel_id": null,
        "device_id": 100111,
        "devicetype_id": "Pointcast V1",
        "height": 5,
        "id": 67762266,
        "latitude": 32.475932,
        "location_name": null,
        "longitude": 130.607123,
        "original_id": 67762266,
        "sensor_id": null,
        "station_id": null,
        "unit": "cpm",
        "user_id": 759,
        "value": 64.0
    },
    {
        "captured_at": "2016-07-09T09:04:20.000Z",
        "channel_id": null,
        "device_id": 100111,
        "devicetype_id": "Pointcast V1",
        "height": 5,
        "id": 67762206,
        "latitude": 32.475932,
        "location_name": null,
        "longitude": 130.607123,
        "original_id": 67762206,
        "sensor_id": null,
        "station_id": null,
        "unit": "cpm",
        "user_id": 759,
        "value": 58.0
    },
    {
        "captured_at": "2016-07-09T09:24:43.000Z",
        "channel_id": null,
        "device_id": 100111,
        "devicetype_id": "Pointcast V1",
        "height": 5,
        "id": 67762444,
        "latitude": 32.475932,
        "location_name": null,
        "longitude": 130.607123,
        "original_id": 67762444,
        "sensor_id": null,
        "station_id": null,
        "unit": "cpm",
        "user_id": 759,
        "value": 59.0
    },
    {
        "captured_at": "2016-07-09T09:34:54.000Z",
        "channel_id": null,
        "device_id": 100111,
        "devicetype_id": "Pointcast V1",
        "height": 5,
        "id": 67762562,
        "latitude": 32.475932,
        "location_name": null,
        "longitude": 130.607123,
        "original_id": 67762562,
        "sensor_id": null,
        "station_id": null,
        "unit": "cpm",
        "user_id": 759,
        "value": 61.0
    },
    {
        "captured_at": "2016-07-09T09:14:32.000Z",
        "channel_id": null,
        "device_id": 100111,
        "devicetype_id": "Pointcast V1",
        "height": 5,
        "id": 67762325,
        "latitude": 32.475932,
        "location_name": null,
        "longitude": 130.607123,
        "original_id": 67762325,
        "sensor_id": null,
        "station_id": null,
        "unit": "cpm",
        "user_id": 759,
        "value": 60.0
    },
    {
        "captured_at": "2016-07-09T09:19:38.000Z",
        "channel_id": null,
        "device_id": 100111,
        "devicetype_id": "Pointcast V1",
        "height": 5,
        "id": 67762385,
        "latitude": 32.475932,
        "location_name": null,
        "longitude": 130.607123,
        "original_id": 67762385,
        "sensor_id": null,
        "station_id": null,
        "unit": "cpm",
        "user_id": 759,
        "value": 77.0
    },
    {
        "captured_at": "2016-07-09T09:50:12.000Z",
        "channel_id": null,
        "device_id": 100111,
        "devicetype_id": "Pointcast V1",
        "height": 5,
        "id": 67762740,
        "latitude": 32.475932,
        "location_name": null,
        "longitude": 130.607123,
        "original_id": 67762740,
        "sensor_id": null,
        "station_id": null,
        "unit": "cpm",
        "user_id": 759,
        "value": 61.0
    },
    {
        "captured_at": "2016-07-09T09:29:48.000Z",
        "channel_id": null,
        "device_id": 100111,
        "devicetype_id": "Pointcast V1",
        "height": 5,
        "id": 67762503,
        "latitude": 32.475932,
        "location_name": null,
        "longitude": 130.607123,
        "original_id": 67762503,
        "sensor_id": null,
        "station_id": null,
        "unit": "cpm",
        "user_id": 759,
        "value": 57.0
    },
    {
        "captured_at": "2016-07-09T09:40:00.000Z",
        "channel_id": null,
        "device_id": 100111,
        "devicetype_id": "Pointcast V1",
        "height": 5,
        "id": 67762621,
        "latitude": 32.475932,
        "location_name": null,
        "longitude": 130.607123,
        "original_id": 67762621,
        "sensor_id": null,
        "station_id": null,
        "unit": "cpm",
        "user_id": 759,
        "value": 50.0
    }
]