[
    {
        "captured_at": "2016-05-31T18:23:06.000Z",
        "channel_id": null,
        "device_id": 100112,
        "devicetype_id": "Pointcast V1",
        "height": 5,
        "id": 65144237,
        "latitude": 32.475932,
        "location_name": null,
        "longitude": 130.607123,
        "original_id": 65144237,
        "sensor_id": null,
        "station_id": null,
        "unit": "cpm",
        "user_id": 759,
        "value": 8.0
    },
    {
        "captured_at": "2016-05-31T18:28:12.000Z",
        "channel_id": null,
        "device_id": 100112,
        "devicetype_id": "Pointcast V1",
        "height": 5,
        "id": 65144292,
        "latitude": 32.475932,
        "location_name": null,
        "longitude": 130.607123,
        "original_id": 65144292,
        "sensor_id": null,
        "station_id": null,
        "unit": "cpm",
        "user_id": 759,
        "value": 6.0
    },
    {
        "captured_at": "2016-05-31T18:12:56.000Z",
        "channel_id": null,
        "device_id": 100112,
        "devicetype_id": "Pointcast V1",
        "height": 5,
        "id": 65144120,
        "latitude": 32.475932,
        "location_name": null,
        "longitude": 130.607123,
        "original_id": 65144120,
        "sensor_id": null,
        "station_id": null,
        "unit": "cpm",
        "user_id": 759,
        "value": 22.0
    },
    {
        "captured_at": "2016-05-31T18:18:01.000Z",
        "channel_id": null,
        "device_id": 100112,
        "devicetype_id": "Pointcast V1",
        "height": 5,
        "id": 65144179,
        "latitude": 32.475932,
        "location_name": null,
        "longitude": 130.607123,
        "original_id": 65144179,
        "sensor_id": null,
        "station_id": null,
        "unit": "cpm",
        "user_id": 759,
        "value": 5.0
    },
    {
        "captured_at": "2016-05-31T18:33:17.000Z",
        "channel_id": null,
        "device_id": 100112,
        "devicetype_id": "Pointcast V1",
        "height": 5,
        "id": 65144349,
        "latitude": 32.475932,
        "location_name": null,
        "longitude": 130.607123,
        "original_id": 65144349,
        "sensor_id": null,
        "station_id": null,
        "unit": "cpm",
        "user_id": 759,
        "value": 12.0
    },
    {
        "captured_at": "2016-05-31T18:38:22.000Z",
        "channel_id": null,
        "device_id": 100112,
        "devicetype_id": "Pointcast V1",
        "height": 5,
        "id": 65144406,
        "latitude": 32.475932,
        "location_name": null,
        "longitude": 130.607123,
        "original_id": 65144406,
        "sensor_id": null,
        "station_id": null,
        "unit": "cpm",
        "user_id": 759,
        "value": 18.0
    },
    {
        "captured_at": "2016-05-31T19:03:52.000Z",
        "channel_id": null,
        "device_id": 100112,
        "devicetype_id": "Pointcast V1",
        "height": 5,
        "id": 65144695,
        "latitude": 32.475932,
        "location_name": null,
        "longitude": 130.607123,
        "original_id": 65144695,
        "sensor_id": null,
        "station_id": null,
        "unit": "cpm",
        "user_id": 759,
        "value": 11.0
    },
    {
        "captured_at": "2016-05-31T18:53:40.000Z",
        "channel_id": null,
        "device_id": 100112,
        "devicetype_id": "Pointcast V1",
        "height": 5,
        "id": 65144580,
        "latitude": 32.475932,
        "location_name": null,
        "longitude": 130.607123,
        "original_id": 65144580,
        "sensor_id": null,
        "station_id": null,
        "unit": "cpm",
        "user_id": 759,
        "value": 10.0
    },
    {
        "captured_at": "2016-05-31T18:43:30.000Z",
        "channel_id": null,
        "device_id": 100112,
        "devicetype_id": "Pointcast V1",
        "height": 5,
        "id": 65144464,
        "latitude": 32.475932,
        "location_name": null,
        "longitude": 130.607123,
        "original_id": 65144464,
        "sensor_id": null,
        "station_id": null,
        "unit": "cpm",
        "user_id": 759,
        "value": 12.0
    },
    {
        "captured_at": "2016-05-31T18:48:35.000Z",
        "channel_id": null,
        "device_id": 100112,
        "devicetype_id": "Pointcast V1",
        "height": 5,
        "id": 65144522,
        "latitude": 32.475932,
        "location_name": null,
        "longitude": 130.607123,
        "original_id": 65144522,
        "sensor_id": null,
        "station_id": null,
        "unit": "cpm",
        "user_id": 759,
        "value": 12.0
    },
    {
        "captured_at": "2016-05-31T18:58:46.000Z",
        "channel_id": null,
        "device_id": 100112,
        "devicetype_id": "Pointcast V1",
        "height": 5,
        "id": 65144639,
        "latitude": 32.475932,
        "location_name": null,
        "longitude": 130.607123,
        "original_id": 65144639,
        "sensor_id": null,
        "station_id": null,
        "unit": "cpm",
        "user_id": 759,
        "value": 19.0
    },
    {
        "captured_at": "2016-05-31T19:14:07.000Z",
        "channel_id": null,
        "device_id": 100112,
        "devicetype_id": "Pointcast V1",
        "height": 5,
        "id": 65144809,
        "latitude": 32.475932,
        "location_name": null,
        "longitude": 130.607123,
        "original_id": 65144809,
        "sensor_id": null,
        "station_id": null,
        "unit": "cpm",
        "user_id": 759,
        "value": 12.0
    },
    {
        "captured_at": "2016-05-31T19:08:59.000Z",
        "channel_id": null,
        "device_id": 100112,
        "devicetype_id": "Pointcast V1",
        "height": 5,
        "id": 65144752,
        "latitude": 32.475932,
        "location_name": null,
        "longitude": 130.607123,
        "original_id": 65144752,
        "sensor_id": null,
        "station_id": null,
        "unit": "cpm",
        "user_id": 759,
        "value": 10.0
    },
    {
        "captured_at": "2016-05-31T19:29:25.000Z",
        "channel_id": null,
        "device_id": 100112,
        "devicetype_id": "Pointcast V1",
        "height": 5,
        "id": 65144989,
        "latitude": 32.475932,
        "location_name": null,
        "longitude": 130.607123,
        "original_id": 65144989,
        "sensor_id": null,
        "station_id": null,
        "unit": "cpm",
        "user_id": 759,
        "value": 13.0
    },
    {
        "captured_at": "2016-05-31T19:34:30.000Z",
        "channel_id": null,
        "device_id": 100112,
        "devicetype_id": "Pointcast V1",
        "height": 5,
        "id": 65145042,
        "latitude": 32.475932,
        "location_name": null,
        "longitude": 130.607123,
        "original_id": 65145042,
        "sensor_id": null,
        "station_id": null,
        "unit": "cpm",
        "user_id": 759,
        "value": 19.0
    },
    {
        "captured_at": "2016-05-31T19:19:13.000Z",
        "channel_id": null,
        "device_id": 100112,
        "devicetype_id": "Pointcast V1",
        "height": 5,
        "id": 65144873,
        "latitude": 32.475932,
        "location_name": null,
        "longitude": 130.607123,
        "original_id": 65144873,
        "sensor_id": null,
        "station_id": null,
        "unit": "cpm",
        "user_id": 759,
        "value": 9.0
    },
    {
        "captured_at": "2016-05-31T19:24:19.000Z",
        "channel_id": null,
        "device_id": 100112,
        "devicetype_id": "Pointcast V1",
        "height": 5,
        "id": 65144928,
        "latitude": 32.475932,
        "location_name": null,
        "longitude": 130.607123,
        "original_id": 65144928,
        "sensor_id": null,
        "station_id": null,
        "unit": "cpm",
        "user_id": 759,
        "value": 14.0
    },
    {
        "captured_at": "2016-05-31T19:44:40.000Z",
        "channel_id": null,
        "device_id": 100112,
        "devicetype_id": "Pointcast V1",
        "height": 5,
        "id": 65145159,
        "latitude": 32.475932,
        "location_name": null,
        "longitude": 130.607123,
        "original_id": 65145159,
        "sensor_id": null,
        "station_id": null,
        "unit": "cpm",
        "user_id": 759,
        "value": 15.0
    },
    {
        "captured_at": "2016-05-31T19:39:35.000Z",
        "channel_id": null,
        "device_id": 100112,
        "devicetype_id": "Pointcast V1",
        "height": 5,
        "id": 65145102,
        "latitude": 32.475932,
        "location_name": null,
        "longitude": 130.607123,
        "original_id": 65145102,
        "sensor_id": null,
        "station_id": null,
        "unit": "cpm",
        "user_id": 759,
        "value": 8.0
    },
    {
        "captured_at": "2016-05-31T19:59:56.000Z",
        "channel_id": null,
        "device_id": 100112,
        "devicetype_id": "Pointcast V1",
        "height": 5,
        "id": 65145338,
        "latitude": 32.475932,
        "location_name": null,
        "longitude": 130.607123,
        "original_id": 65145338,
        "sensor_id": null,
        "station_id": null,
        "unit": "cpm",
        "user_id": 759,
        "value": 15.0
    },
    {
        "captured_at": "2016-05-31T19:49:45.000Z",
        "channel_id": null,
        "device_id": 100112,
        "devicetype_id": "Pointcast V1",
        "height": 5,
        "id": 65145218,
        "latitude": 32.475932,
        "location_name": null,
        "longitude": 130.607123,
        "original_id": 65145218,
        "sensor_id": null,
        "station_id": null,
        "unit": "cpm",
        "user_id": 759,
        "value": 14.0
    },
    {
        "captured_at": "2016-05-31T19:54:50.000Z",
        "channel_id": null,
        "device_id": 100112,
        "devicetype_id": "Pointcast V1",
        "height": 5,
        "id": 65145275,
        "latitude": 32.475932,
        "location_name": null,
        "longitude": 130.607123,
        "original_id": 65145275,
        "sensor_id": null,
        "station_id": null,
        "unit": "cpm",
        "user_id": 759,
        "value": 9.0
    },
    {
        "captured_at": "2016-05-31T20:05:01.000Z",
        "channel_id": null,
        "device_id": 100112,
        "devicetype_id": "Pointcast V1",
        "height": 5,
        "id": 65146495,
        "latitude": 32.475932,
        "location_name": null,
        "longitude": 130.607123,
        "original_id": 65146495,
        "sensor_id": null,
        "station_id": null,
        "unit": "cpm",
        "user_id": 759,
        "value": 14.0
    },
    {
        "captured_at": "2016-05-31T20:10:07.000Z",
        "channel_id": null,
        "device_id": 100112,
        "devicetype_id": "Pointcast V1",
        "height": 5,
        "id": 65146553,
        "latitude": 32.475932,
        "location_name": null,
        "longitude": 130.607123,
        "original_id": 65146553,
        "sensor_id": null,
        "station_id": null,
        "unit": "cpm",
        "user_id": 759,
        "value": 19.0
    },
    {
        "captured_at": "2016-05-31T20:30:32.000Z",
        "channel_id": null,
        "device_id": 100112,
        "devicetype_id": "Pointcast V1",
        "height": 5,
        "id": 65146792,
        "latitude": 32.475932,
        "location_name": null,
        "longitude": 130.607123,
        "original_id": 65146792,
        "sensor_id": null,
        "station_id": null,
        "unit": "cpm",
        "user_id": 759,
        "value": 7.0
    }
]