[
    {
        "captured_at": "2016-06-17T20:39:25.000Z",
        "channel_id": null,
        "device_id": 100112,
        "devicetype_id": "Pointcast V1",
        "height": 5,
        "id": 66872097,
        "latitude": 32.475932,
        "location_name": null,
        "longitude": 130.607123,
        "original_id": null,
        "sensor_id": null,
        "station_id": null,
        "unit": "cpm",
        "user_id": 759,
        "value": 8.0
    },
    {
        "captured_at": "2016-06-17T20:59:48.000Z",
        "channel_id": null,
        "device_id": 100112,
        "devicetype_id": "Pointcast V1",
        "height": 5,
        "id": 66872329,
        "latitude": 32.475932,
        "location_name": null,
        "longitude": 130.607123,
        "original_id": null,
        "sensor_id": null,
        "station_id": null,
        "unit": "cpm",
        "user_id": 759,
        "value": 7.0
    },
    {
        "captured_at": "2016-06-17T21:20:12.000Z",
        "channel_id": null,
        "device_id": 100112,
        "devicetype_id": "Pointcast V1",
        "height": 5,
        "id": 66872563,
        "latitude": 32.475932,
        "location_name": null,
        "longitude": 130.607123,
        "original_id": null,
        "sensor_id": null,
        "station_id": null,
        "unit": "cpm",
        "user_id": 759,
        "value": 13.0
    },
    {
        "captured_at": "2016-06-17T21:25:17.000Z",
        "channel_id": null,
        "device_id": 100112,
        "devicetype_id": "Pointcast V1",
        "height": 5,
        "id": 66872621,
        "latitude": 32.475932,
        "location_name": null,
        "longitude": 130.607123,
        "original_id": null,
        "sensor_id": null,
        "station_id": null,
        "unit": "cpm",
        "user_id": 759,
        "value": 7.0
    },
    {
        "captured_at": "2016-06-17T21:04:54.000Z",
        "channel_id": null,
        "device_id": 100112,
        "devicetype_id": "Pointcast V1",
        "height": 5,
        "id": 66872388,
        "latitude": 32.475932,
        "location_name": null,
        "longitude": 130.607123,
        "original_id": null,
        "sensor_id": null,
        "station_id": null,
        "unit": "cpm",
        "user_id": 759,
        "value": 9.0
    },
    {
        "captured_at": "2016-06-17T21:15:06.000Z",
        "channel_id": null,
        "device_id": 100112,
        "devicetype_id": "Pointcast V1",
        "height": 5,
        "id": 66872506,
        "latitude": 32.475932,
        "location_name": null,
        "longitude": 130.607123,
        "original_id": null,
        "sensor_id": null,
        "station_id": null,
        "unit": "cpm",
        "user_id": 759,
        "value": 7.0
    },
    {
        "captured_at": "2016-06-17T21:30:22.000Z",
        "channel_id": null,
        "device_id": 100112,
        "devicetype_id": "Pointcast V1",
        "height": 5,
        "id": 66872680,
        "latitude": 32.475932,
        "location_name": null,
        "longitude": 130.607123,
        "original_id": null,
        "sensor_id": null,
        "station_id": null,
        "unit": "cpm",
        "user_id": 759,
        "value": 7.0
    },
    {
        "captured_at": "2016-06-17T21:10:00.000Z",
        "channel_id": null,
        "device_id": 100112,
        "devicetype_id": "Pointcast V1",
        "height": 5,
        "id": 66872449,
        "latitude": 32.475932,
        "location_name": null,
        "longitude": 130.607123,
        "original_id": null,
        "sensor_id": null,
        "station_id": null,
        "unit": "cpm",
        "user_id": 759,
        "value": 11.0
    },
    {
        "captured_at": "2016-06-17T21:35:29.000Z",
        "channel_id": null,
        "device_id": 100112,
        "devicetype_id": "Pointcast V1",
        "height": 5,
        "id": 66872738,
        "latitude": 32.475932,
        "location_name": null,
        "longitude": 130.607123,
        "original_id": null,
        "sensor_id": null,
        "station_id": null,
        "unit": "cpm",
        "user_id": 759,
        "value": 9.0
    },
    {
        "captured_at": "2016-06-17T21:50:48.000Z",
        "channel_id": null,
        "device_id": 100112,
        "devicetype_id": "Pointcast V1",
        "height": 5,
        "id": 66872912,
        "latitude": 32.475932,
        "location_name": null,
        "longitude": 130.607123,
        "original_id": null,
        "sensor_id": null,
        "station_id": null,
        "unit": "cpm",
        "user_id": 759,
        "value": 10.0
    },
    {
        "captured_at": "2016-06-17T22:01:06.000Z",
        "channel_id": null,
        "device_id": 100112,
        "devicetype_id": "Pointcast V1",
        "height": 5,
        "id": 66873029,
        "latitude": 32.475932,
        "location_name": null,
        "longitude": 130.607123,
        "original_id": null,
        "sensor_id": null,
        "station_id": null,
        "unit": "cpm",
        "user_id": 759,
        "value": 11.0
    },
    {
        "captured_at": "2016-06-17T21:40:36.000Z",
        "channel_id": null,
        "device_id": 100112,
        "devicetype_id": "Pointcast V1",
        "height": 5,
        "id": 66872796,
        "latitude": 32.475932,
        "location_name": null,
        "longitude": 130.607123,
        "original_id": null,
        "sensor_id": null,
        "station_id": null,
        "unit": "cpm",
        "user_id": 759,
        "value": 5.0
    },
    {
        "captured_at": "2016-06-17T22:06:14.000Z",
        "channel_id": null,
        "device_id": 100112,
        "devicetype_id": "Pointcast V1",
        "height": 5,
        "id": 66873091,
        "latitude": 32.475932,
        "location_name": null,
        "longitude": 130.607123,
        "original_id": null,
        "sensor_id": null,
        "station_id": null,
        "unit": "cpm",
        "user_id": 759,
        "value": 16.0
    },
    {
        "captured_at": "2016-06-17T21:45:43.000Z",
        "channel_id": null,
        "device_id": 100112,
        "devicetype_id": "Pointcast V1",
        "height": 5,
        "id": 66872854,
        "latitude": 32.475932,
        "location_name": null,
        "longitude": 130.607123,
        "original_id": null,
        "sensor_id": null,
        "station_id": null,
        "unit": "cpm",
        "user_id": 759,
        "value": 5.0
    },
    {
        "captured_at": "2016-06-17T22:11:19.000Z",
        "channel_id": null,
        "device_id": 100112,
        "devicetype_id": "Pointcast V1",
        "height": 5,
        "id": 66873150,
        "latitude": 32.475932,
        "location_name": null,
        "longitude": 130.607123,
        "original_id": null,
        "sensor_id": null,
        "station_id": null,
        "unit": "cpm",
        "user_id": 759,
        "value": 9.0
    },
    {
        "captured_at": "2016-06-17T21:55:53.000Z",
        "channel_id": null,
        "device_id": 100112,
        "devicetype_id": "Pointcast V1",
        "height": 5,
        "id": 66872970,
        "latitude": 32.475932,
        "location_name": null,
        "longitude": 130.607123,
        "original_id": null,
        "sensor_id": null,
        "station_id": null,
        "unit": "cpm",
        "user_id": 759,
        "value": 14.0
    },
    {
        "captured_at": "2016-06-17T22:16:25.000Z",
        "channel_id": null,
        "device_id": 100112,
        "devicetype_id": "Pointcast V1",
        "height": 5,
        "id": 66873208,
        "latitude": 32.475932,
        "location_name": null,
        "longitude": 130.607123,
        "original_id": null,
        "sensor_id": null,
        "station_id": null,
        "unit": "cpm",
        "user_id": 759,
        "value": 8.0
    },
    {
        "captured_at": "2016-06-17T22:21:30.000Z",
        "channel_id": null,
        "device_id": 100112,
        "devicetype_id": "Pointcast V1",
        "height": 5,
        "id": 66873266,
        "latitude": 32.475932,
        "location_name": null,
        "longitude": 130.607123,
        "original_id": null,
        "sensor_id": null,
        "station_id": null,
        "unit": "cpm",
        "user_id": 759,
        "value": 10.0
    },
    {
        "captured_at": "2016-06-17T22:26:37.000Z",
        "channel_id": null,
        "device_id": 100112,
        "devicetype_id": "Pointcast V1",
        "height": 5,
        "id": 66873327,
        "latitude": 32.475932,
        "location_name": null,
        "longitude": 130.607123,
        "original_id": null,
        "sensor_id": null,
        "station_id": null,
        "unit": "cpm",
        "user_id": 759,
        "value": 8.0
    },
    {
        "captured_at": "2016-06-17T22:36:51.000Z",
        "channel_id": null,
        "device_id": 100112,
        "devicetype_id": "Pointcast V1",
        "height": 5,
        "id": 66873443,
        "latitude": 32.475932,
        "location_name": null,
        "longitude": 130.607123,
        "original_id": null,
        "sensor_id": null,
        "station_id": null,
        "unit": "cpm",
        "user_id": 759,
        "value": 8.0
    },
    {
        "captured_at": "2016-06-17T22:31:45.000Z",
        "channel_id": null,
        "device_id": 100112,
        "devicetype_id": "Pointcast V1",
        "height": 5,
        "id": 66873381,
        "latitude": 32.475932,
        "location_name": null,
        "longitude": 130.607123,
        "original_id": null,
        "sensor_id": null,
        "station_id": null,
        "unit": "cpm",
        "user_id": 759,
        "value": 11.0
    },
    {
        "captured_at": "2016-06-17T22:47:03.000Z",
        "channel_id": null,
        "device_id": 100112,
        "devicetype_id": "Pointcast V1",
        "height": 5,
        "id": 66873562,
        "latitude": 32.475932,
        "location_name": null,
        "longitude": 130.607123,
        "original_id": null,
        "sensor_id": null,
        "station_id": null,
        "unit": "cpm",
        "user_id": 759,
        "value": 3.0
    },
    {
        "captured_at": "2016-06-17T22:41:58.000Z",
        "channel_id": null,
        "device_id": 100112,
        "devicetype_id": "Pointcast V1",
        "height": 5,
        "id": 66873503,
        "latitude": 32.475932,
        "location_name": null,
        "longitude": 130.607123,
        "original_id": null,
        "sensor_id": null,
        "station_id": null,
        "unit": "cpm",
        "user_id": 759,
        "value": 5.0
    },
    {
        "captured_at": "2016-06-17T23:02:17.000Z",
        "channel_id": null,
        "device_id": 100112,
        "devicetype_id": "Pointcast V1",
        "height": 5,
        "id": 66873737,
        "latitude": 32.475932,
        "location_name": null,
        "longitude": 130.607123,
        "original_id": null,
        "sensor_id": null,
        "station_id": null,
        "unit": "cpm",
        "user_id": 759,
        "value": 5.0
    },
    {
        "captured_at": "2016-06-17T22:52:07.000Z",
        "channel_id": null,
        "device_id": 100112,
        "devicetype_id": "Pointcast V1",
        "height": 5,
        "id": 66873620,
        "latitude": 32.475932,
        "location_name": null,
        "longitude": 130.607123,
        "original_id": null,
        "sensor_id": null,
        "station_id": null,
        "unit": "cpm",
        "user_id": 759,
        "value": 8.0
    }
]