[
    {
        "captured_at": "2016-06-12T10:29:07.000Z",
        "channel_id": null,
        "device_id": 100221,
        "devicetype_id": "Pointcast V1",
        "height": 13,
        "id": 66594716,
        "latitude": 31.833193,
        "location_name": null,
        "longitude": 130.301922,
        "original_id": null,
        "sensor_id": null,
        "station_id": null,
        "unit": "cpm",
        "user_id": 759,
        "value": 36.0
    },
    {
        "captured_at": "2016-06-12T10:59:24.000Z",
        "channel_id": null,
        "device_id": 100221,
        "devicetype_id": "Pointcast V1",
        "height": 13,
        "id": 66595071,
        "latitude": 31.833193,
        "location_name": null,
        "longitude": 130.301922,
        "original_id": null,
        "sensor_id": null,
        "station_id": null,
        "unit": "cpm",
        "user_id": 759,
        "value": 27.0
    },
    {
        "captured_at": "2016-06-12T10:49:18.000Z",
        "channel_id": null,
        "device_id": 100221,
        "devicetype_id": "Pointcast V1",
        "height": 13,
        "id": 66594951,
        "latitude": 31.833193,
        "location_name": null,
        "longitude": 130.301922,
        "original_id": null,
        "sensor_id": null,
        "station_id": null,
        "unit": "cpm",
        "user_id": 759,
        "value": 40.0
    },
    {
        "captured_at": "2016-06-12T10:54:21.000Z",
        "channel_id": null,
        "device_id": 100221,
        "devicetype_id": "Pointcast V1",
        "height": 13,
        "id": 66595011,
        "latitude": 31.833193,
        "location_name": null,
        "longitude": 130.301922,
        "original_id": null,
        "sensor_id": null,
        "station_id": null,
        "unit": "cpm",
        "user_id": 759,
        "value": 47.0
    },
    {
        "captured_at": "2016-06-12T11:04:26.000Z",
        "channel_id": null,
        "device_id": 100221,
        "devicetype_id": "Pointcast V1",
        "height": 13,
        "id": 66595127,
        "latitude": 31.833193,
        "location_name": null,
        "longitude": 130.301922,
        "original_id": null,
        "sensor_id": null,
        "station_id": null,
        "unit": "cpm",
        "user_id": 759,
        "value": 37.0
    },
    {
        "captured_at": "2016-06-12T11:19:35.000Z",
        "channel_id": null,
        "device_id": 100221,
        "devicetype_id": "Pointcast V1",
        "height": 13,
        "id": 66595299,
        "latitude": 31.833193,
        "location_name": null,
        "longitude": 130.301922,
        "original_id": null,
        "sensor_id": null,
        "station_id": null,
        "unit": "cpm",
        "user_id": 759,
        "value": 32.0
    },
    {
        "captured_at": "2016-06-12T11:09:29.000Z",
        "channel_id": null,
        "device_id": 100221,
        "devicetype_id": "Pointcast V1",
        "height": 13,
        "id": 66595185,
        "latitude": 31.833193,
        "location_name": null,
        "longitude": 130.301922,
        "original_id": null,
        "sensor_id": null,
        "station_id": null,
        "unit": "cpm",
        "user_id": 759,
        "value": 42.0
    },
    {
        "captured_at": "2016-06-12T11:14:32.000Z",
        "channel_id": null,
        "device_id": 100221,
        "devicetype_id": "Pointcast V1",
        "height": 13,
        "id": 66595242,
        "latitude": 31.833193,
        "location_name": null,
        "longitude": 130.301922,
        "original_id": null,
        "sensor_id": null,
        "station_id": null,
        "unit": "cpm",
        "user_id": 759,
        "value": 38.0
    },
    {
        "captured_at": "2016-06-12T11:24:37.000Z",
        "channel_id": null,
        "device_id": 100221,
        "devicetype_id": "Pointcast V1",
        "height": 13,
        "id": 66595356,
        "latitude": 31.833193,
        "location_name": null,
        "longitude": 130.301922,
        "original_id": null,
        "sensor_id": null,
        "station_id": null,
        "unit": "cpm",
        "user_id": 759,
        "value": 25.0
    },
    {
        "captured_at": "2016-06-12T11:44:48.000Z",
        "channel_id": null,
        "device_id": 100221,
        "devicetype_id": "Pointcast V1",
        "height": 13,
        "id": 66595586,
        "latitude": 31.833193,
        "location_name": null,
        "longitude": 130.301922,
        "original_id": null,
        "sensor_id": null,
        "station_id": null,
        "unit": "cpm",
        "user_id": 759,
        "value": 31.0
    },
    {
        "captured_at": "2016-06-12T11:34:43.000Z",
        "channel_id": null,
        "device_id": 100221,
        "devicetype_id": "Pointcast V1",
        "height": 13,
        "id": 66595469,
        "latitude": 31.833193,
        "location_name": null,
        "longitude": 130.301922,
        "original_id": null,
        "sensor_id": null,
        "station_id": null,
        "unit": "cpm",
        "user_id": 759,
        "value": 39.0
    },
    {
        "captured_at": "2016-06-12T11:29:40.000Z",
        "channel_id": null,
        "device_id": 100221,
        "devicetype_id": "Pointcast V1",
        "height": 13,
        "id": 66595410,
        "latitude": 31.833193,
        "location_name": null,
        "longitude": 130.301922,
        "original_id": null,
        "sensor_id": null,
        "station_id": null,
        "unit": "cpm",
        "user_id": 759,
        "value": 30.0
    },
    {
        "captured_at": "2016-06-12T11:39:45.000Z",
        "channel_id": null,
        "device_id": 100221,
        "devicetype_id": "Pointcast V1",
        "height": 13,
        "id": 66595527,
        "latitude": 31.833193,
        "location_name": null,
        "longitude": 130.301922,
        "original_id": null,
        "sensor_id": null,
        "station_id": null,
        "unit": "cpm",
        "user_id": 759,
        "value": 42.0
    },
    {
        "captured_at": "2016-06-12T11:49:51.000Z",
        "channel_id": null,
        "device_id": 100221,
        "devicetype_id": "Pointcast V1",
        "height": 13,
        "id": 66595641,
        "latitude": 31.833193,
        "location_name": null,
        "longitude": 130.301922,
        "original_id": null,
        "sensor_id": null,
        "station_id": null,
        "unit": "cpm",
        "user_id": 759,
        "value": 28.0
    },
    {
        "captured_at": "2016-06-12T11:54:54.000Z",
        "channel_id": null,
        "device_id": 100221,
        "devicetype_id": "Pointcast V1",
        "height": 13,
        "id": 66595693,
        "latitude": 31.833193,
        "location_name": null,
        "longitude": 130.301922,
        "original_id": null,
        "sensor_id": null,
        "station_id": null,
        "unit": "cpm",
        "user_id": 759,
        "value": 36.0
    },
    {
        "captured_at": "2016-06-12T12:10:02.000Z",
        "channel_id": null,
        "device_id": 100221,
        "devicetype_id": "Pointcast V1",
        "height": 13,
        "id": 66595768,
        "latitude": 31.833193,
        "location_name": null,
        "longitude": 130.301922,
        "original_id": null,
        "sensor_id": null,
        "station_id": null,
        "unit": "cpm",
        "user_id": 759,
        "value": 42.0
    },
    {
        "captured_at": "2016-06-12T12:25:12.000Z",
        "channel_id": null,
        "device_id": 100221,
        "devicetype_id": "Pointcast V1",
        "height": 13,
        "id": 66595934,
        "latitude": 31.833193,
        "location_name": null,
        "longitude": 130.301922,
        "original_id": null,
        "sensor_id": null,
        "station_id": null,
        "unit": "cpm",
        "user_id": 759,
        "value": 34.0
    },
    {
        "captured_at": "2016-06-12T12:20:09.000Z",
        "channel_id": null,
        "device_id": 100221,
        "devicetype_id": "Pointcast V1",
        "height": 13,
        "id": 66595877,
        "latitude": 31.833193,
        "location_name": null,
        "longitude": 130.301922,
        "original_id": null,
        "sensor_id": null,
        "station_id": null,
        "unit": "cpm",
        "user_id": 759,
        "value": 33.0
    },
    {
        "captured_at": "2016-06-12T12:15:06.000Z",
        "channel_id": null,
        "device_id": 100221,
        "devicetype_id": "Pointcast V1",
        "height": 13,
        "id": 66595824,
        "latitude": 31.833193,
        "location_name": null,
        "longitude": 130.301922,
        "original_id": null,
        "sensor_id": null,
        "station_id": null,
        "unit": "cpm",
        "user_id": 759,
        "value": 31.0
    },
    {
        "captured_at": "2016-06-12T12:30:15.000Z",
        "channel_id": null,
        "device_id": 100221,
        "devicetype_id": "Pointcast V1",
        "height": 13,
        "id": 66595991,
        "latitude": 31.833193,
        "location_name": null,
        "longitude": 130.301922,
        "original_id": null,
        "sensor_id": null,
        "station_id": null,
        "unit": "cpm",
        "user_id": 759,
        "value": 35.0
    },
    {
        "captured_at": "2016-06-12T12:45:24.000Z",
        "channel_id": null,
        "device_id": 100221,
        "devicetype_id": "Pointcast V1",
        "height": 13,
        "id": 66596160,
        "latitude": 31.833193,
        "location_name": null,
        "longitude": 130.301922,
        "original_id": null,
        "sensor_id": null,
        "station_id": null,
        "unit": "cpm",
        "user_id": 759,
        "value": 35.0
    },
    {
        "captured_at": "2016-06-12T12:35:18.000Z",
        "channel_id": null,
        "device_id": 100221,
        "devicetype_id": "Pointcast V1",
        "height": 13,
        "id": 66596046,
        "latitude": 31.833193,
        "location_name": null,
        "longitude": 130.301922,
        "original_id": null,
        "sensor_id": null,
        "station_id": null,
        "unit": "cpm",
        "user_id": 759,
        "value": 28.0
    },
    {
        "captured_at": "2016-06-12T12:40:21.000Z",
        "channel_id": null,
        "device_id": 100221,
        "devicetype_id": "Pointcast V1",
        "height": 13,
        "id": 66596103,
        "latitude": 31.833193,
        "location_name": null,
        "longitude": 130.301922,
        "original_id": null,
        "sensor_id": null,
        "station_id": null,
        "unit": "cpm",
        "user_id": 759,
        "value": 41.0
    },
    {
        "captured_at": "2016-06-12T12:55:29.000Z",
        "channel_id": null,
        "device_id": 100221,
        "devicetype_id": "Pointcast V1",
        "height": 13,
        "id": 66596273,
        "latitude": 31.833193,
        "location_name": null,
        "longitude": 130.301922,
        "original_id": null,
        "sensor_id": null,
        "station_id": null,
        "unit": "cpm",
        "user_id": 759,
        "value": 43.0
    },
    {
        "captured_at": "2016-06-12T12:50:26.000Z",
        "channel_id": null,
        "device_id": 100221,
        "devicetype_id": "Pointcast V1",
        "height": 13,
        "id": 66596217,
        "latitude": 31.833193,
        "location_name": null,
        "longitude": 130.301922,
        "original_id": null,
        "sensor_id": null,
        "station_id": null,
        "unit": "cpm",
        "user_id": 759,
        "value": 29.0
    }
]